{
  "root": "E:/zlecenia/forestGroup",
  "modules": [
    {
      "id": "\u0000vite/modulepreload-polyfill.js",
      "deps": [],
      "plugins": [
        {
          "name": "vite:modulepreload-polyfill",
          "transform": 0
        },
        {
          "name": "vite:modulepreload-polyfill",
          "resolveId": 0
        },
        {
          "name": "vite:modulepreload-polyfill",
          "resolveId": 0
        },
        {
          "name": "vite:modulepreload-polyfill",
          "resolveId": 0
        }
      ],
      "virtual": true,
      "totalTime": 0,
      "invokeCount": 1,
      "sourceSize": 1280,
      "distSize": 1280
    },
    {
      "id": "E:/zlecenia/forestGroup/assets/js/main.js",
      "deps": [],
      "plugins": [
        {
          "name": "vite:load-fallback",
          "transform": 16
        },
        {
          "name": "vite:resolve",
          "resolveId": 1
        },
        {
          "name": "vite:resolve",
          "resolveId": 0
        },
        {
          "name": "vite:resolve",
          "resolveId": 0
        }
      ],
      "virtual": false,
      "totalTime": 16,
      "invokeCount": 1,
      "sourceSize": 4740,
      "distSize": 0
    },
    {
      "id": "E:/zlecenia/forestGroup/assets/scss/_about.scss",
      "deps": [],
      "plugins": [
        {
          "name": "vite:load-fallback",
          "transform": 6
        },
        {
          "name": "vite:css",
          "transform": 636
        },
        {
          "name": "vite:resolve",
          "resolveId": 1
        }
      ],
      "virtual": false,
      "totalTime": 642,
      "invokeCount": 1,
      "sourceSize": 610,
      "distSize": 0
    },
    {
      "id": "E:/zlecenia/forestGroup/assets/scss/_animations.scss",
      "deps": [],
      "plugins": [
        {
          "name": "vite:load-fallback",
          "transform": 6
        },
        {
          "name": "vite:css",
          "transform": 636
        },
        {
          "name": "vite:resolve",
          "resolveId": 1
        }
      ],
      "virtual": false,
      "totalTime": 642,
      "invokeCount": 1,
      "sourceSize": 550,
      "distSize": 0
    },
    {
      "id": "E:/zlecenia/forestGroup/assets/scss/_contact.scss",
      "deps": [],
      "plugins": [
        {
          "name": "vite:load-fallback",
          "transform": 7
        },
        {
          "name": "vite:css",
          "transform": 635
        },
        {
          "name": "vite:resolve",
          "resolveId": 0
        }
      ],
      "virtual": false,
      "totalTime": 642,
      "invokeCount": 1,
      "sourceSize": 249,
      "distSize": 0
    },
    {
      "id": "E:/zlecenia/forestGroup/assets/scss/_fonts.scss",
      "deps": [],
      "plugins": [
        {
          "name": "vite:load-fallback",
          "transform": 5
        },
        {
          "name": "vite:css",
          "transform": 655
        },
        {
          "name": "vite:resolve",
          "resolveId": 3
        }
      ],
      "virtual": false,
      "totalTime": 660,
      "invokeCount": 1,
      "sourceSize": 464,
      "distSize": 0
    },
    {
      "id": "E:/zlecenia/forestGroup/assets/scss/_footer.scss",
      "deps": [],
      "plugins": [
        {
          "name": "vite:load-fallback",
          "transform": 6
        },
        {
          "name": "vite:css",
          "transform": 635
        },
        {
          "name": "vite:resolve",
          "resolveId": 0
        }
      ],
      "virtual": false,
      "totalTime": 641,
      "invokeCount": 1,
      "sourceSize": 1777,
      "distSize": 0
    },
    {
      "id": "E:/zlecenia/forestGroup/assets/scss/_globals.scss",
      "deps": [],
      "plugins": [
        {
          "name": "vite:load-fallback",
          "transform": 5
        },
        {
          "name": "vite:css",
          "transform": 637
        },
        {
          "name": "vite:resolve",
          "resolveId": 2
        }
      ],
      "virtual": false,
      "totalTime": 642,
      "invokeCount": 1,
      "sourceSize": 1291,
      "distSize": 0
    },
    {
      "id": "E:/zlecenia/forestGroup/assets/scss/_header.scss",
      "deps": [],
      "plugins": [
        {
          "name": "vite:load-fallback",
          "transform": 6
        },
        {
          "name": "vite:css",
          "transform": 652
        },
        {
          "name": "vite:resolve",
          "resolveId": 1
        }
      ],
      "virtual": false,
      "totalTime": 658,
      "invokeCount": 1,
      "sourceSize": 1233,
      "distSize": 0
    },
    {
      "id": "E:/zlecenia/forestGroup/assets/scss/_media.scss",
      "deps": [],
      "plugins": [
        {
          "name": "vite:load-fallback",
          "transform": 7
        },
        {
          "name": "vite:css",
          "transform": 654
        },
        {
          "name": "vite:resolve",
          "resolveId": 0
        }
      ],
      "virtual": false,
      "totalTime": 661,
      "invokeCount": 1,
      "sourceSize": 3426,
      "distSize": 0
    },
    {
      "id": "E:/zlecenia/forestGroup/assets/scss/_mixins.scss",
      "deps": [],
      "plugins": [
        {
          "name": "vite:load-fallback",
          "transform": 5
        },
        {
          "name": "vite:resolve",
          "resolveId": 2
        }
      ],
      "virtual": false,
      "totalTime": 5,
      "invokeCount": 1,
      "sourceSize": 1133,
      "distSize": 0
    },
    {
      "id": "E:/zlecenia/forestGroup/assets/scss/_nav.scss",
      "deps": [],
      "plugins": [
        {
          "name": "vite:load-fallback",
          "transform": 5
        },
        {
          "name": "vite:css",
          "transform": 636
        },
        {
          "name": "vite:resolve",
          "resolveId": 2
        }
      ],
      "virtual": false,
      "totalTime": 641,
      "invokeCount": 1,
      "sourceSize": 2794,
      "distSize": 0
    },
    {
      "id": "E:/zlecenia/forestGroup/assets/scss/_offersSection.scss",
      "deps": [],
      "plugins": [
        {
          "name": "vite:load-fallback",
          "transform": 6
        },
        {
          "name": "vite:css",
          "transform": 636
        },
        {
          "name": "vite:resolve",
          "resolveId": 1
        }
      ],
      "virtual": false,
      "totalTime": 642,
      "invokeCount": 1,
      "sourceSize": 2616,
      "distSize": 0
    },
    {
      "id": "E:/zlecenia/forestGroup/assets/scss/_parallax.scss",
      "deps": [],
      "plugins": [
        {
          "name": "vite:load-fallback",
          "transform": 6
        },
        {
          "name": "vite:css",
          "transform": 650
        },
        {
          "name": "vite:resolve",
          "resolveId": 1
        }
      ],
      "virtual": false,
      "totalTime": 656,
      "invokeCount": 1,
      "sourceSize": 1348,
      "distSize": 0
    },
    {
      "id": "E:/zlecenia/forestGroup/assets/scss/_reset.scss",
      "deps": [],
      "plugins": [
        {
          "name": "vite:load-fallback",
          "transform": 5
        },
        {
          "name": "vite:css",
          "transform": 637
        },
        {
          "name": "vite:resolve",
          "resolveId": 3
        }
      ],
      "virtual": false,
      "totalTime": 642,
      "invokeCount": 1,
      "sourceSize": 152,
      "distSize": 0
    },
    {
      "id": "E:/zlecenia/forestGroup/assets/scss/main.scss",
      "deps": [],
      "plugins": [
        {
          "name": "vite:load-fallback",
          "transform": 3
        },
        {
          "name": "vite:css",
          "transform": 639
        },
        {
          "name": "vite:resolve",
          "resolveId": 4
        }
      ],
      "virtual": false,
      "totalTime": 642,
      "invokeCount": 1,
      "sourceSize": 443,
      "distSize": 0
    },
    {
      "id": "E:/zlecenia/forestGroup/contact.html",
      "deps": [],
      "plugins": [
        {
          "name": "vite:load-fallback",
          "transform": 14
        },
        {
          "name": "vite:build-html",
          "transform": 78
        },
        {
          "name": "vite:resolve",
          "resolveId": 0
        }
      ],
      "virtual": false,
      "totalTime": 92,
      "invokeCount": 1,
      "sourceSize": 6837,
      "distSize": 0
    },
    {
      "id": "E:/zlecenia/forestGroup/index.html",
      "deps": [],
      "plugins": [
        {
          "name": "vite:load-fallback",
          "transform": 19
        },
        {
          "name": "vite:build-html",
          "transform": 81
        },
        {
          "name": "vite:resolve",
          "resolveId": 1
        }
      ],
      "virtual": false,
      "totalTime": 100,
      "invokeCount": 1,
      "sourceSize": 10006,
      "distSize": 0
    },
    {
      "id": "E:/zlecenia/forestGroup/offers.html",
      "deps": [],
      "plugins": [
        {
          "name": "vite:load-fallback",
          "transform": 20
        },
        {
          "name": "vite:build-html",
          "transform": 100
        },
        {
          "name": "vite:resolve",
          "resolveId": 0
        }
      ],
      "virtual": false,
      "totalTime": 120,
      "invokeCount": 1,
      "sourceSize": 8060,
      "distSize": 0
    }
  ],
  "ssrModules": []
}
